anki_helper/__init__.py
anki_helper/builder.py
anki_helper/config.py
anki_helper/json_reader.py
anki_helper/main.py
anki_helper/model.py
anki_helper/template.py
ankihelper-0.1.2.dist-info/METADATA
ankihelper-0.1.2.dist-info/WHEEL
ankihelper-0.1.2.dist-info/entry_points.txt
ankihelper-0.1.2.dist-info/licenses/LICENSE
ankihelper-0.1.2.dist-info/RECORD
