Metadata-Version: 2.1
Name: AnkiHelper
Version: 0.1.2
Summary: Default template for PDM package
Author-Email: =?utf-8?b?7IKw7JeQ7IKs64qU6rCA7J6s?= <qhals8380@gmail.com>
License: MIT
Requires-Python: >=3.9
Requires-Dist: argparse>=1.4.0
Requires-Dist: genanki>=0.13.1
